weaviate_mcp/__init__.py
weaviate_mcp/__main__.py
weaviate_mcp/app.py
weaviate_mcp/auth.py
weaviate_mcp/config.py
weaviate_mcp/resources/__init__.py
weaviate_mcp/resources/schema_resource.py
weaviate_mcp/services/__init__.py
weaviate_mcp/services/ingestion_service.py
weaviate_mcp/services/weaviate_service.py
weaviate_mcp/tools/__init__.py
weaviate_mcp/tools/collection_tools.py
weaviate_mcp/tools/data_tools.py
weaviate_mcp/tools/ingestion_tools.py
weaviate_mcp/tools/schema_tools.py
weaviate_mcp-0.1.5.dist-info/METADATA
weaviate_mcp-0.1.5.dist-info/WHEEL
weaviate_mcp-0.1.5.dist-info/entry_points.txt
weaviate_mcp-0.1.5.dist-info/RECORD
