Metadata-Version: 2.4
Name: weaviate-mcp
Version: 0.1.5
Summary: MCP server for Weaviate vector database
Author-email: Arclio Team <info@arclio.com>
License: MIT
Requires-Python: >=3.10
Requires-Dist: beautifulsoup4>=4.12.0
Requires-Dist: httpx>=0.27.0
Requires-Dist: mcp>=1.7.0
Requires-Dist: tiktoken>=0.5.0
Requires-Dist: weaviate-client>=4.9.3
Provides-Extra: dev
